tgext/__init__.py
tgext/tw2/__init__.py
tgext/tw2/component.py
tgext/tw2/validation.py
tgext.tw2-0.1.dist-info/LICENSE
tgext.tw2-0.1.dist-info/METADATA
tgext.tw2-0.1.dist-info/WHEEL
tgext.tw2-0.1.dist-info/top_level.txt
tgext.tw2-0.1.dist-info/RECORD
