Metadata-Version: 2.1
Name: tgext.tw2
Version: 0.1
Summary: Enable support for ToscaWidgets2 form and validation library
Author-email: Alessandro Molina <amol@turbogears.org>
Keywords: turbogears2.extension
Requires-Python: >=3.7
License-File: LICENSE
Requires-Dist: tw2.core
Requires-Dist: TurboGears2 >=2.5.0
